colors_terminal/__init__.py
Colors_Terminal-0.0.4.dist-info/LICENSE
Colors_Terminal-0.0.4.dist-info/METADATA
Colors_Terminal-0.0.4.dist-info/WHEEL
Colors_Terminal-0.0.4.dist-info/top_level.txt
Colors_Terminal-0.0.4.dist-info/RECORD
