Metadata-Version: 2.1
Name: Colors-Terminal
Version: 0.0.4
Summary: colors_terminal this tool help decorate your terminal in Python fast and easy :)
Home-page: https://github.com/xXBlackDev9010Xx/colors_terminal
Author: xXBlackDev9010Xx
Author-email: tecnoblue9010@gmail.com
Classifier: Programming Language :: Python :: 3
Classifier: License :: OSI Approved :: MIT License
Classifier: Operating System :: OS Independent
Requires-Python: >=3.7
License-File: LICENSE
